{"users":[{"email":"blblbl@gmail.com","password":"$2a$10$DF3WWarUllGXYUDvly/f2ebfQeTjt/gKKkp8sySav0GgKvVHYwQS.","nome":"Marcelo","descricaoPerfil":"bal bal bal bal balb a","guthub":"github.com/maeceloacm1998","id":1},{"email":"blblbl@gmail.co","password":"$2a$10$D2irPeRym4UefLjYTPKQtOBYRQg37bnA1GiGbpeLljOA9sdqGbQNa","nome":"Marcelo","descricaoPerfil":"bal bal bal bal balb a","guthub":"github.com/maeceloacm1998","id":2},{"id":3,"email":"blblbl@gmail.co","password":"12345","nome":"Marcelo","descricaoPerfil":"bal bal bal bal balb a"},{"id":4,"email":"teste@teste.com","password":"123453","nome":"Karen e Claudia","descricaoPerfil":"bal bal"},{"id":5,"email":"teste@teste.com","password":"123453","nome":"Karen e Claudia","descricaoPerfil":"bal bal"},{"id":6,"email":"teste@teste.com","password":"123453","nome":"Karen e Claudia","descricaoPerfil":"bal bal","github":"github.com/maeceloacm1998"},{"id":7,"email":"teste@teste.com","password":"123453","nome":"Marcelo","descricaoPerfil":"bal bal","github":"github.com/maeceloacm1998"},{"id":8,"email":"teste@teste.com","password":"123453","nome":"Marcelo","descricaoPerfil":"bal bal","github":"github.com/maeceloacm1998"},{"id":9,"email":"teste@teste.com","password":"123453","nome":"Marcelo","descricaoPerfil":"bal bal","github":"github.com/maeceloacm1998"},{"id":10,"email":"teste@teste.com","password":"123453","nome":"Marcelo","descricaoPerfil":"bal bal","github":"github.com/maeceloacm1998"},{"id":11,"email":"teste@teste.com","password":"123453","nome":"Marcelo","descricaoPerfil":"bal bal","github":"github.com/maeceloacm1998"},{"id":12,"email":"teste@teste.com","password":"123453","nome":"Marcelo","descricaoPerfil":"bal bal","github":"github.com/maeceloacm1998"},{"id":13,"email":"teste@teste.com","password":"123453","nome":"Marcelo","descricaoPerfil":"bal bal","github":"github.com/maeceloacm1998"},{"id":14,"email":"teste@teste.com","password":"123453","nome":"Marcelo","descricaoPerfil":"bal bal","github":"github.com/maeceloacm1998"},{"id":15,"email":"teste@teste.com","password":"123453","nome":"Marcelo","descricaoPerfil":"bal bal","github":"github.com/maeceloacm1998"},{"id":16,"email":"teste@teste.comm","password":"123453","nome":"Marcelooo","descricaoPerfil":"bal bal","github":"github.com/maeceloacm1998"},{"id":17,"email":"teste@teste.commm","password":"123453","nome":"Marcelooo","descricaoPerfil":"bal bal","github":"github.com/maeceloacm1998"},{"id":18,"email":"teste@teste.commm","password":"123453","nome":"Marcelooo","descricaoPerfil":"bal bal","github":"github.com/maeceloacm1998"},{"id":19,"email":"teste@teste.commm","password":"123453","nome":"Marcelooo","descricaoPerfil":"bal bal","github":"github.com/maeceloacm1998"},{"id":20,"email":"teste@teste.commmm","password":"123453","nome":"Marcelooo","descricaoPerfil":"bal bal","github":"github.com/maeceloacm1998"},{"id":21,"email":"teste@teste.commmm","password":"123453","nome":"Marcelooo","descricaoPerfil":"bal bal","github":"github.com/maeceloacm1998"},{"id":22,"email":"teste@teste.commmmm","password":"123453","nome":"Marcelooo","descricaoPerfil":"bal bal","github":"github.com/maeceloacm1998"},{"id":23,"email":"teste@teste.","password":"123453","nome":"Marcelooo","descricaoPerfil":"bal bal","github":"github.com/maeceloacm1998"},{"id":24,"email":"teste@teste","password":"123453","nome":"Marcelooo","descricaoPerfil":"bal bal","github":"github.com/maeceloacm1998"},{"id":25,"email":"teste@test","password":"123453","nome":"Marcelooo","descricaoPerfil":"bal bal","github":"github.com/maeceloacm1998"},{"id":26,"email":"teste@tes","password":"123453","nome":"Marcelooo","descricaoPerfil":"bal bal","github":"github.com/maeceloacm1998"},{"id":27,"email":"teste@ts","password":"123453","nome":"Marcelooo","descricaoPerfil":"bal bal","github":"github.com/maeceloacm1998"}],"gastos":[{"id":1,"tipo":0,"data":"01/01/2022","preco":6.77,"valor":100,"odometro":33000},{"id":2,"tipo":1,"data":"10/01/2022","preco":5.65,"valor":100,"odometro":32000},{"tipo":1,"data":"10/01/2022","preco":7.5,"valor":130,"odometro":34000,"id":3}]}